mbr_test_pckg/__init__.py
mbr_test_pckg/show_py_interpreter.py
mbr_test_pckg-1.1.0.dist-info/METADATA
mbr_test_pckg-1.1.0.dist-info/WHEEL
mbr_test_pckg-1.1.0.dist-info/top_level.txt
mbr_test_pckg-1.1.0.dist-info/RECORD
