Metadata-Version: 2.4
Name: mbr-test-pckg
Version: 1.1.0
Summary: My first package!
Author-email: Milan Brzon <mbrzon@gmail.com>
